balderhub/snmpagent/__init__.py
balderhub/snmpagent/_version.py
balderhub/snmpagent/lib/__init__.py
balderhub/snmpagent/lib/connections.py
balderhub/snmpagent/lib/features/__init__.py
balderhub/snmpagent/lib/features/has_snmp_system_group_feature.py
balderhub/snmpagent/lib/features/send_snmp_get_request_command_feature.py
balderhub/snmpagent/lib/features/send_snmp_set_request_command_feature.py
balderhub/snmpagent/lib/features/snmp_system_config.py
balderhub/snmpagent/lib/setup_features/__init__.py
balderhub/snmpagent/lib/setup_features/send_snmp_get_request_pysnmp_feature.py
balderhub/snmpagent/lib/setup_features/send_snmp_set_request_pysnmp_feature.py
balderhub/snmpagent/lib/utils/__init__.py
balderhub/snmpagent/lib/utils/pysnmp_utilities.py
balderhub/snmpagent/lib/utils/snmp_package.py
balderhub/snmpagent/scenarios/__init__.py
balderhub/snmpagent/scenarios/base/__init__.py
balderhub/snmpagent/scenarios/base/scenario_mib_sys_descr.py
balderhub/snmpagent/scenarios/base/scenario_mib_sys_object_id.py
balderhub/snmpagent/scenarios/base/scenario_mib_sys_up_time.py
balderhub_snmpagent-0.0.1b0.dist-info/LICENSE
balderhub_snmpagent-0.0.1b0.dist-info/METADATA
balderhub_snmpagent-0.0.1b0.dist-info/WHEEL
balderhub_snmpagent-0.0.1b0.dist-info/top_level.txt
balderhub_snmpagent-0.0.1b0.dist-info/RECORD
