Metadata-Version: 2.1
Name: balderhub-snmpagent
Version: 0.0.1b0
Summary: balderhub-snmpagent: balderhub package for testing snmp agents
Home-page: https://hub.balder.dev/snmpagent
Author: Max Stahlschmidt and others
License: MIT
Project-URL: Source, https://github.com/balder-dev/balderhub-snmpagent
Project-URL: Tracker, https://github.com/balder-dev/balderhub-snmpagent/issues
Keywords: test,systemtest,reusable,scenario,junit,balder
Platform: unix
Platform: linux
Platform: osx
Platform: cygwin
Platform: win32
Classifier: License :: OSI Approved :: MIT License
Classifier: Operating System :: MacOS :: MacOS X
Classifier: Operating System :: Microsoft :: Windows
Classifier: Operating System :: POSIX
Classifier: Intended Audience :: Developers
Classifier: Programming Language :: Python :: 3
Classifier: Programming Language :: Python :: 3 :: Only
Classifier: Programming Language :: Python :: 3.9
Classifier: Programming Language :: Python :: 3.10
Classifier: Topic :: Software Development :: Libraries
Classifier: Topic :: Software Development :: Testing
Classifier: Topic :: Utilities
Requires-Python: >=3.9
License-File: LICENSE
Requires-Dist: baldertest (>=0.1.0b5)
Requires-Dist: pysnmp (>=4.4.12)
